envrotate/__init__.py
envrotate/core.py
envrotate-0.1.1.dist-info/METADATA
envrotate-0.1.1.dist-info/WHEEL
envrotate-0.1.1.dist-info/top_level.txt
envrotate-0.1.1.dist-info/RECORD
