Metadata-Version: 2.4
Name: envrotate
Version: 0.1.1
Summary: Rotate environment variables (e.g., API keys) with cooldown intervals
Author: Cauan
License: MIT
Project-URL: Homepage, https://github.com/cauan/envrotate
Project-URL: Repository, https://github.com/cauan/envrotate
Keywords: api,keys,rotation,env,environment-variables
Classifier: Programming Language :: Python :: 3
Classifier: License :: OSI Approved :: MIT License
Classifier: Operating System :: OS Independent
Requires-Python: >=3.7
